<?xml version="1.0" encoding="UTF-8"?>
<biblioteca xmlns:lib="http://www.ejemplo.com/libros" xmlns:auto="http://www.ejemplo.com/autores">
    <lib:libros>
        <lib:titulo>El Quijote</lib:titulo>
        <lib:editorial>Penguin Books</lib:editorial> 
    <auto:autores >
        <auto:nombre>Miguel de Cervantes</auto:nombre>
        <auto:nacionalidad>Español</auto:nacionalidad>
    </auto:autores>
    </lib:libros>

    <lib:libros>
        <lib:titulo>Cien años de soledad</lib:titulo>
        <lib:editorial>Penguin Random House</lib:editorial> 
    <auto:autores >
        <auto:nombre>Gabriel García</auto:nombre>
        <auto:nacionalidad>Colombiano</auto:nacionalidad>
    </auto:autores>
    </lib:libros>
</biblioteca>